{
  "bookName": "",
  "bookNameEnglish": "Jonah",
  "contents": [
    {
      "chapter": 1,
      "verses": [
        {
          "verseNumber": 1,
          "text": "¶ 主(あるじ)の言葉(ことば)がアミッタイの子(こ)ヨナに臨(のぞ)んで言(い)った、"
        },
        {
          "verseNumber": 2,
          "text": "「立(た)って、あの大(おお)きな町(まち)ニネベに行(い)き、これに向(む)かって呼(よ)ばわれ。彼(かれ)らの悪(あく)がわたしの前(まえ)に上(のぼ)ってきたからである」。"
        },
        {
          "verseNumber": 3,
          "text": "しかしヨナは主(おも)の前(まえ)を離(はな)れてタルシシへのがれようと、立(た)ってヨッパに下(くだ)って行(い)った。ところがちょうど、タルシシへ行(い)く船(ふね)があったので、船賃(ふなちん)を払(はら)い、主(あるじ)の前(まえ)を離(はな)れて、人々(ひとびと)と共(とも)にタルシシへ行(い)こうと船(ふね)に乗(の)った。"
        },
        {
          "verseNumber": 4,
          "text": "時(とき)に、主(おも)は大風(おおかぜ)を海(うみ)の上(うえ)に起(おこ)されたので、船(ふね)が破(わ)れるほどの激(はげ)しい暴風(ぼうふう)が海(うみ)の上(うえ)にあった。"
        },
        {
          "verseNumber": 5,
          "text": "それで水夫(すいふ)たちは恐(おそ)れて、めいめい自分(じぶん)の神(かみ)を呼(よ)び求(もと)め、また船(ふね)を軽(かる)くするため、その中(なか)の積(つ)み荷(に)を海(うみ)に投(な)げ捨(す)てた。しかし、ヨナは船(ふね)の奥(おく)に下(くだ)り、伏(ふ)して熟睡(じゅくすい)していた。"
        },
        {
          "verseNumber": 6,
          "text": "そこで船長(せんちょう)は来(き)て、彼(かれ)に言(い)った、「あなたはどうして眠(ねむ)っているのか。起(お)きて、あなたの神(かみ)に呼(よ)ばわりなさい。神(かみ)があるいは、われわれを顧(かえり)みて、助(たす)けてくださるだろう」。"
        },
        {
          "verseNumber": 7,
          "text": "やがて人々(ひとびと)は互(かたみ)に言(い)った、「この災(わざわい)がわれわれに臨(のぞ)んだのは、だれのせいか知(し)るために、さあ、くじを引(ひ)いてみよう」。そして彼(かれ)らが、くじを引(ひ)いたところ、くじはヨナに当(あた)った。"
        },
        {
          "verseNumber": 8,
          "text": "そこで人々(ひとびと)はヨナに言(い)った、「この災(わざわい)がだれのせいで、われわれに臨(のぞ)んだのか、われわれに告(つ)げなさい。あなたの職業(しょくぎょう)は何(なに)か。あなたはどこから来(き)たのか。あなたの国(くに)はどこか。あなたはどこの民(みん)か」。"
        },
        {
          "verseNumber": 9,
          "text": "ヨナは彼(かれ)らに言(い)った、「わたしはヘブルびとです。わたしは海(うみ)と陸(りく)とをお造(つく)りになった天(てん)の神(かみ)、主(あるじ)を恐(おそ)れる者(もの)です」。"
        },
        {
          "verseNumber": 10,
          "text": "そこで人々(ひとびと)ははなはだしく恐(おそ)れて、彼(かれ)に言(い)った、「あなたはなんたる事(こと)をしてくれたのか」。人々(ひとびと)は彼(かれ)がさきに彼(かれ)らに告(つ)げた事(こと)によって、彼(かれ)が主(おも)の前(まえ)を離(はな)れて、のがれようとしていた事(こと)を知(し)っていたからである。"
        },
        {
          "verseNumber": 11,
          "text": "人々(ひとびと)は彼(かれ)に言(い)った、「われわれのために海(うみ)が静(しず)まるには、あなたをどうしたらよかろうか」。それは海(うみ)がますます荒(あ)れてきたからである。"
        },
        {
          "verseNumber": 12,
          "text": "ヨナは彼(かれ)らに言(い)った、「わたしを取(と)って海(うみ)に投(な)げ入(い)れなさい。そうしたら海(うみ)は、あなたがたのために静(しず)まるでしょう。わたしにはよくわかっています。この激(はげ)しい暴風(ぼうふう)があなたがたに臨(のぞ)んだのは、わたしのせいです」。"
        },
        {
          "verseNumber": 13,
          "text": "しかし人々(ひとびと)は船(ふね)を陸(りく)にこぎもどそうとつとめたが、成功(せいこう)しなかった。それは海(うみ)が彼(かれ)らに逆(さか)らって、いよいよ荒(あ)れたからである。"
        },
        {
          "verseNumber": 14,
          "text": "そこで人々(ひとびと)は主(おも)に呼(よ)ばわって言(い)った、「主(おも)よ、どうぞ、この人(ひと)の生命(せいめい)のために、われわれを滅(ほろ)ぼさないでください。また罪(つみ)なき血(ち)を、われわれに帰(き)しないでください。主(おも)よ、これはみ心(しん)に従(したが)って、なされた事(こと)だからです」。"
        },
        {
          "verseNumber": 15,
          "text": "そして彼(かれ)らはヨナを取(と)って海(うみ)に投(な)げ入(い)れた。すると海(うみ)の荒(あ)れるのがやんだ。"
        },
        {
          "verseNumber": 16,
          "text": "そこで人々(ひとびと)は大(おお)いに主(おも)を恐(おそ)れ、犠牲(ぎせい)を主(おも)にささげて、誓願(せいがん)を立(た)てた。"
        },
        {
          "verseNumber": 17,
          "text": "主(おも)は大(おお)いなる魚(さかな)を備(そな)えて、ヨナをのませられた。ヨナは三(さん)日(にち)三(さん)夜(や)その魚(さかな)の腹(はら)の中(うち)にいた。"
        }
      ]
    },
    {
      "chapter": 2,
      "verses": [
        {
          "verseNumber": 1,
          "text": "ヨナは魚(さかな)の腹(はら)の中(うち)からその神(かみ)、主(おも)に祈(いの)って、"
        },
        {
          "verseNumber": 2,
          "text": "言(い)った、 「わたしは悩(なや)みのうちから主(あるじ)に呼(よ)ばわると、 主(おも)はわたしに答(こた)えられた。 わたしが陰(かげ)府(ふ)の腹(はら)の中(うち)から叫(さけ)ぶと、 あなたはわたしの声(こえ)を聞(き)かれた。"
        },
        {
          "verseNumber": 3,
          "text": "あなたはわたしを淵(ふち)の中(なか)、 海(うみ)のまん中(なか)に投(な)げ入(い)れられた。 大水(おおみず)はわたしをめぐり、 あなたの波(なみ)と大波(おおなみ)は皆(みな)、わたしの上(うえ)を越(こ)えて行(い)った。"
        },
        {
          "verseNumber": 4,
          "text": "わたしは言(い)った、 『わたしはあなたの前(まえ)から追(お)われてしまった、 どうして再(ふたた)びあなたの聖(せい)なる宮(みや)を望(のぞ)みえようか』。"
        },
        {
          "verseNumber": 5,
          "text": "水(みず)がわたしをめぐって魂(たましい)にまでおよび、 淵(ふち)はわたしを取(と)り囲(かこ)み、 海草(かいそう)は山(やま)の根元(ねもと)でわたしの頭(あたま)にまといついた。"
        },
        {
          "verseNumber": 6,
          "text": "わたしは地(ち)に下(くだ)り、 地(ち)の貫(かん)の木(き)はいつもわたしの上(うえ)にあった。 しかしわが神(かみ)、主(おも)よ、 あなたはわが命(いのち)を穴(あな)から救(すく)いあげられた。"
        },
        {
          "verseNumber": 7,
          "text": "わが魂(たましい)がわたしのうちに弱(よわ)っているとき、 わたしは主(おも)をおぼえ、 わたしの祈(いの)はあなたに至(いた)り、 あなたの聖(せい)なる宮(みや)に達(たっ)した。"
        },
        {
          "verseNumber": 8,
          "text": "むなしい偶像(ぐうぞう)に心(こころ)を寄(よ)せる者(もの)は、 そのまことの忠節(ちゅうせつ)を捨(す)てる。"
        },
        {
          "verseNumber": 9,
          "text": "しかしわたしは感謝(かんしゃ)の声(こえ)をもって、 あなたに犠牲(ぎせい)をささげ、わたしの誓(ちか)いをはたす。 救(救)は主(おも)にある」。"
        },
        {
          "verseNumber": 10,
          "text": "主(おも)は魚(さかな)にお命(めい)じになったので、魚(さかな)はヨナを陸(りく)に吐(は)き出(だ)した。"
        }
      ]
    },
    {
      "chapter": 3,
      "verses": [
        {
          "verseNumber": 1,
          "text": "時(とき)に主(おも)の言葉(ことば)は再(ふたた)びヨナに臨(のぞ)んで言(い)った、"
        },
        {
          "verseNumber": 2,
          "text": "「立(た)って、あの大(おお)きな町(まち)ニネベに行(い)き、あなたに命(めい)じる言葉(ことば)をこれに伝(つた)えよ」。"
        },
        {
          "verseNumber": 3,
          "text": "そこでヨナは主(おも)の言葉(ことば)に従(したが)い、立(た)って、ニネベに行(い)った。ニネベは非常(ひじょう)に大(おお)きな町(まち)であって、これを行(い)きめぐるには、三(さん)日(にち)を要(よう)するほどであった。"
        },
        {
          "verseNumber": 4,
          "text": "ヨナはその町(まち)にはいり、初(はじ)め一(いち)日(にち)路(ろ)を行(い)きめぐって呼(よ)ばわり、「四(よん)十(じゅう)日(にち)を経(へ)たらニネベは滅(ほろ)びる」と言(い)った。"
        },
        {
          "verseNumber": 5,
          "text": "そこでニネベの人々(ひとびと)は神(かみ)を信(しん)じ、断食(だんじき)をふれ、大(おお)きい者(もの)から小(ちい)さい者(もの)まで荒布(あらめ)を着(き)た。"
        },
        {
          "verseNumber": 6,
          "text": "このうわさがニネベの王(おう)に達(たっ)すると、彼(かれ)はその王座(おうざ)から立(た)ち上(あ)がり、朝(あさ)服(ふく)を脱(ぬ)ぎ、荒布(あらめ)をまとい、灰(はい)の中(なか)に座(ざ)した。"
        },
        {
          "verseNumber": 7,
          "text": "また王(おう)とその大臣(だいじん)の布告(ふこく)をもって、ニネベ中(ちゅう)にふれさせて言(い)った、「人(ひと)も獣(しし)も牛(うし)も羊(ひつじ)もみな、何(なに)をも味(あじ)わってはならない。物(もの)を食(く)い、水(みず)を飲(の)んではならない。"
        },
        {
          "verseNumber": 8,
          "text": "人(ひと)も獣(しし)も荒布(あらめ)をまとい、ひたすら神(かみ)に呼(よ)ばわり、おのおのその悪(わる)い道(みち)およびその手(て)にある強暴(きょうぼう)を離(はな)れよ。"
        },
        {
          "verseNumber": 9,
          "text": "あるいは神(かみ)はみ心(しん)をかえ、その激(はげ)しい怒(いか)りをやめて、われわれを滅(ほろ)ぼされないかもしれない。だれがそれを知(し)るだろう」。"
        },
        {
          "verseNumber": 10,
          "text": "神(かみ)は彼(かれ)らのなすところ、その悪(わる)い道(みち)を離(はな)れたのを見(み)られ、彼(かれ)らの上(うえ)に下(くだ)そうと言(い)われた災(わざわい)を思(おも)いかえして、これをおやめになった。"
        }
      ]
    },
    {
      "chapter": 4,
      "verses": [
        {
          "verseNumber": 1,
          "text": "ところがヨナはこれを非常(ひじょう)に不快(ふかい)として、激(はげ)しく怒(おこ)り、"
        },
        {
          "verseNumber": 2,
          "text": "主(おも)に祈(いの)って言(い)った、「主(おも)よ、わたしがなお国(くに)におりました時(とき)、この事(こと)を申(もう)したではありませんか。それでこそわたしは、急(いそ)いでタルシシにのがれようとしたのです。なぜなら、わたしはあなたが恵(めぐ)み深(ふか)い神(かみ)、あわれみあり、怒(おこ)ることおそく、いつくしみ豊(ゆた)かで、災(わざわい)を思(おも)いかえされることを、知(し)っていたからです。"
        },
        {
          "verseNumber": 3,
          "text": "それで主(おも)よ、どうぞ今(いま)わたしの命(いのち)をとってください。わたしにとっては、生(い)きるよりも死(し)ぬ方(ほう)がましだからです」。"
        },
        {
          "verseNumber": 4,
          "text": "主(おも)は言(い)われた、「あなたの怒(おこ)るのは、よいことであろうか」。"
        },
        {
          "verseNumber": 5,
          "text": "そこでヨナは町(まち)から出(で)て、町(まち)の東(ひがし)の方(ほう)に座(ざ)し、そこに自分(じぶん)のために一(ひと)つの小屋(こや)を造(つく)り、町(まち)のなりゆきを見(み)きわめようと、その下(した)の日陰(ひかげ)にすわっていた。"
        },
        {
          "verseNumber": 6,
          "text": "時(とき)に主(おも)なる神(かみ)は、ヨナを暑(あつ)さの苦痛(くつう)から救(すく)うために、とうごまを備(そな)えて、それを育(そだ)て、ヨナの頭(あたま)の上(うえ)に日陰(ひかげ)を設(もう)けた。ヨナはこのとうごまを非常(ひじょう)に喜(よろこ)んだ。"
        },
        {
          "verseNumber": 7,
          "text": "ところが神(かみ)は翌日(よくじつ)の夜明(よあ)けに虫(むし)を備(そな)えて、そのとうごまをかませられたので、それは枯(か)れた。"
        },
        {
          "verseNumber": 8,
          "text": "やがて太陽(たいよう)が出(で)たとき、神(かみ)が暑(あつ)い東風(こち)を備(そな)え、また太陽(たいよう)がヨナの頭(あたま)を照(あきら)したので、ヨナは弱(よわ)りはて、死(し)ぬことを願(ねが)って言(い)った、「生(い)きるよりも死(し)ぬ方(ほう)がわたしにはましだ」。"
        },
        {
          "verseNumber": 9,
          "text": "しかし神(かみ)はヨナに言(い)われた、「とうごまのためにあなたの怒(おこ)るのはよくない」。ヨナは言(い)った、「わたしは怒(いか)りのあまり狂(くる)い死(し)にそうです」。"
        },
        {
          "verseNumber": 10,
          "text": "主(おも)は言(い)われた、「あなたは労(ろう)せず、育(そだ)てず、一夜(いちや)に生(しょう)じて、一夜(いちや)に滅(ほろ)びたこのとうごまをさえ、惜(お)しんでいる。"
        },
        {
          "verseNumber": 11,
          "text": "ましてわたしは十(じゅう)二(に)万(まん)あまりの、右左(みぎひだり)をわきまえない人々(ひとびと)と、あまたの家畜(かちく)とのいるこの大(おお)きな町(まち)ニネベを、惜(お)しまないでいられようか」。"
        }
      ]
    }
  ]
}